dy_wake/__init__.py
dy_wake-0.0.1.dist-info/METADATA
dy_wake-0.0.1.dist-info/WHEEL
dy_wake-0.0.1.dist-info/RECORD
